tests/__init__.py
tests/test_edit_handler.py
tests/app/__init__.py
tests/app/models.py
tests/app/settings.py
tests/app/urls.py
tests/app/migrations/0001_initial.py
tests/app/migrations/__init__.py
wagtailannotatedimage/__init__.py
wagtailannotatedimage/edit_handlers.py
wagtailannotatedimage/fields.py
wagtailannotatedimage/forms.py
wagtailannotatedimage/views.py
wagtailannotatedimage/wagtail_hooks.py
wagtailannotatedimage/static/annotated-image/annotated-image-handler.js
wagtailannotatedimage/static/annotated-image/annotated-image.css
wagtailannotatedimage/static/annotated-image/jquery.annotate.js
wagtailannotatedimage/templates/annotated_image.html
wagtailannotatedimage/templates/annotated_image.js
wagtailannotatedimage-2.7.0.dist-info/LICENSE
wagtailannotatedimage-2.7.0.dist-info/METADATA
wagtailannotatedimage-2.7.0.dist-info/WHEEL
wagtailannotatedimage-2.7.0.dist-info/top_level.txt
wagtailannotatedimage-2.7.0.dist-info/RECORD
