Metadata-Version: 2.1
Name: wagtailannotatedimage
Version: 2.7.0
Summary: A wagtail module for creating an image field with annotation metadata
Home-page: https://github.com/neon-jungle/wagtailannotatedimage
Author: Neon Jungle
Author-email: developers@neonjungle.studio
License: BSD License
Platform: UNKNOWN
Classifier: Environment :: Web Environment
Classifier: Intended Audience :: Developers
Classifier: Operating System :: OS Independent
Classifier: Programming Language :: Python
Classifier: Programming Language :: Python :: 2
Classifier: Programming Language :: Python :: 2.7
Classifier: Programming Language :: Python :: 3
Classifier: Programming Language :: Python :: 3.4
Classifier: Programming Language :: Python :: 3.5
Classifier: Framework :: Django
Classifier: License :: OSI Approved :: BSD License
Requires-Dist: Django (>=2.0)
Requires-Dist: wagtail (>=2.7)
Provides-Extra: testing
Requires-Dist: selenium (==3.0.0) ; extra == 'testing'
